{
  "rows": [
    {
      "label": "MNIST Gate1 SGLD r5",
      "dataset": "MNIST",
      "model": "MLP",
      "sampler": "SGLD",
      "source_csv": "runs/mnist_gate1_full_r5_p0p3_summary.csv",
      "num_runs": 5,
      "metrics": {
        "dense_imp_barrier": {
          "n": 5.0,
          "mean": 0.0026406687927246096,
          "std": 0.0037660832943312112,
          "ci95_low": -0.0020347915824796697,
          "ci95_high": 0.007316129167928889
        },
        "dense_sample_barrier": {
          "n": 5.0,
          "mean": 0.8839278878784178,
          "std": 0.14906585056306612,
          "ci95_low": 0.6988678604879445,
          "ci95_high": 1.0689879152688913
        },
        "imp_sample_barrier": {
          "n": 5.0,
          "mean": 0.9391068510131836,
          "std": 0.0927332649493538,
          "ci95_low": 0.8239817537040923,
          "ci95_high": 1.0542319483222748
        },
        "posterior_jaccard": {
          "n": 5.0,
          "mean": 0.23732427345431767,
          "std": 0.0010649141772652224,
          "ci95_low": 0.23600221983795416,
          "ci95_high": 0.23864632707068117
        },
        "chain_start_jaccard": {
          "n": 5.0,
          "mean": 0.2384643876400597,
          "std": 0.001200556383928204,
          "ci95_low": 0.23697393897958957,
          "ci95_high": 0.23995483630052983
        },
        "posterior_minus_chain_start_jaccard": {
          "n": 5.0,
          "mean": -0.0011401141857420361,
          "std": 0.0001619256358018062,
          "ci95_low": -0.001341139185656582,
          "ci95_high": -0.0009390891858274903
        },
        "posterior_to_chain_start_jaccard": {
          "n": 5.0,
          "mean": 0.9297703313813687,
          "std": 0.0007786167642866805,
          "ci95_low": 0.9288037059659479,
          "ci95_high": 0.9307369567967895
        },
        "dense_magnitude_jaccard": {
          "n": 5.0,
          "mean": 0.5924264241128779,
          "std": 0.010898139782796565,
          "ci95_low": 0.578896765649243,
          "ci95_high": 0.6059560825765129
        },
        "random_jaccard": {
          "n": 5.0,
          "mean": 0.09177439971759402,
          "std": 4.3459110472442926e-05,
          "ci95_low": 0.09172044675557074,
          "ci95_high": 0.0918283526796173
        },
        "posterior_minus_random_jaccard": {
          "n": 5.0,
          "mean": 0.14554987373672365,
          "std": 0.0010610838147688114,
          "ci95_low": 0.14423257538111117,
          "ci95_high": 0.14686717209233613
        },
        "state_num_clusters": {
          "n": 5.0,
          "mean": 3.0,
          "std": 0.0,
          "ci95_low": 3.0,
          "ci95_high": 3.0
        },
        "function_num_clusters": {
          "n": 5.0,
          "mean": 3.0,
          "std": 0.0,
          "ci95_low": 3.0,
          "ci95_high": 3.0
        },
        "sample_accuracy": {
          "n": 5.0,
          "mean": 0.9683806666666668,
          "std": 0.000499164023365329,
          "ci95_low": 0.9677609720317963,
          "ci95_high": 0.9690003613015372
        },
        "dense_accuracy": {
          "n": 5.0,
          "mean": 0.9667199999999999,
          "std": 0.0005540758070878329,
          "ci95_low": 0.9660321343107843,
          "ci95_high": 0.9674078656892156
        },
        "imp_accuracy": {
          "n": 5.0,
          "mean": 0.9737600000000001,
          "std": 0.001038267788193388,
          "ci95_low": 0.9724710269414764,
          "ci95_high": 0.9750489730585238
        },
        "sampler_chains": {
          "n": 5.0,
          "mean": 3.0,
          "std": 0.0,
          "ci95_low": 3.0,
          "ci95_high": 3.0
        }
      }
    },
    {
      "label": "Fashion-MNIST Gate1 SGLD r5",
      "dataset": "Fashion-MNIST",
      "model": "MLP",
      "sampler": "SGLD",
      "source_csv": "runs/fashion_gate1_full_r5_p0p3_summary.csv",
      "num_runs": 5,
      "metrics": {
        "dense_imp_barrier": {
          "n": 5.0,
          "mean": 0.03951370727539062,
          "std": 0.03838026221396522,
          "ci95_low": -0.008134042693774816,
          "ci95_high": 0.08716145724455607
        },
        "dense_sample_barrier": {
          "n": 5.0,
          "mean": 0.8330781533203124,
          "std": 0.08088548410493676,
          "ci95_low": 0.7326616605594944,
          "ci95_high": 0.9334946460811304
        },
        "imp_sample_barrier": {
          "n": 5.0,
          "mean": 0.8028503680114746,
          "std": 0.09499085783668706,
          "ci95_low": 0.6849225482814646,
          "ci95_high": 0.9207781877414846
        },
        "posterior_jaccard": {
          "n": 5.0,
          "mean": 0.21144042326275975,
          "std": 0.0022588883919520356,
          "ci95_low": 0.20863609251827572,
          "ci95_high": 0.21424475400724377
        },
        "chain_start_jaccard": {
          "n": 5.0,
          "mean": 0.21219731164909308,
          "std": 0.0021273465318053042,
          "ci95_low": 0.20955628551226935,
          "ci95_high": 0.21483833778591682
        },
        "posterior_minus_chain_start_jaccard": {
          "n": 5.0,
          "mean": -0.0007568883863333375,
          "std": 0.00017721773927733902,
          "ci95_low": -0.0009768979965885513,
          "ci95_high": -0.0005368787760781237
        },
        "posterior_to_chain_start_jaccard": {
          "n": 5.0,
          "mean": 0.9212239165775922,
          "std": 0.0010675081444641,
          "ci95_low": 0.9198986426418929,
          "ci95_high": 0.9225491905132914
        },
        "dense_magnitude_jaccard": {
          "n": 5.0,
          "mean": 0.525518968129918,
          "std": 0.03931187971726971,
          "ci95_low": 0.4767146476918776,
          "ci95_high": 0.5743232885679584
        },
        "random_jaccard": {
          "n": 5.0,
          "mean": 0.09169991645926026,
          "std": 0.00011213974766840266,
          "ci95_low": 0.09156069889402525,
          "ci95_high": 0.09183913402449527
        },
        "posterior_minus_random_jaccard": {
          "n": 5.0,
          "mean": 0.11974050680349949,
          "std": 0.0023205718165274928,
          "ci95_low": 0.11685959824995756,
          "ci95_high": 0.12262141535704141
        },
        "state_num_clusters": {
          "n": 5.0,
          "mean": 3.0,
          "std": 0.0,
          "ci95_low": 3.0,
          "ci95_high": 3.0
        },
        "function_num_clusters": {
          "n": 5.0,
          "mean": 3.0,
          "std": 0.0,
          "ci95_low": 3.0,
          "ci95_high": 3.0
        },
        "sample_accuracy": {
          "n": 5.0,
          "mean": 0.8683726666666667,
          "std": 0.000520542718921589,
          "ci95_low": 0.8677264311307765,
          "ci95_high": 0.8690189022025568
        },
        "dense_accuracy": {
          "n": 5.0,
          "mean": 0.8645799999999999,
          "std": 0.0016269603560013235,
          "ci95_low": 0.8625601857574519,
          "ci95_high": 0.866599814242548
        },
        "imp_accuracy": {
          "n": 5.0,
          "mean": 0.87194,
          "std": 0.0019047309521294637,
          "ci95_low": 0.8695753433006883,
          "ci95_high": 0.8743046566993118
        },
        "sampler_chains": {
          "n": 5.0,
          "mean": 3.0,
          "std": 0.0,
          "ci95_low": 3.0,
          "ci95_high": 3.0
        }
      }
    },
    {
      "label": "CIFAR-10 ResNet-20 long SGLD r5",
      "dataset": "CIFAR-10",
      "model": "ResNet-20",
      "sampler": "SGLD",
      "source_csv": "runs/cifar10_resnet20_long30_rewind1_r5_p0p3_summary.csv",
      "num_runs": 5,
      "metrics": {
        "dense_imp_barrier": {
          "n": 5.0,
          "mean": 3.0827475311279295,
          "std": 0.3993145343902306,
          "ci95_low": 2.58701253620764,
          "ci95_high": 3.578482526048219
        },
        "dense_sample_barrier": {
          "n": 5.0,
          "mean": 2.942803819946289,
          "std": 0.5086482820800179,
          "ci95_low": 2.3113348103891935,
          "ci95_high": 3.5742728295033848
        },
        "imp_sample_barrier": {
          "n": 5.0,
          "mean": 2.6585626706542973,
          "std": 0.2792415946543523,
          "ci95_low": 2.3118940207918603,
          "ci95_high": 3.0052313205167343
        },
        "posterior_jaccard": {
          "n": 5.0,
          "mean": 0.13419037892801328,
          "std": 0.0029624119754536643,
          "ci95_low": 0.1305126483193694,
          "ci95_high": 0.13786810953665715
        },
        "chain_start_jaccard": {
          "n": 5.0,
          "mean": 0.1341904065816573,
          "std": 0.002901187180986115,
          "ci95_low": 0.13058868440887142,
          "ci95_high": 0.13779212875444316
        },
        "posterior_minus_chain_start_jaccard": {
          "n": 5.0,
          "mean": -2.7653644013581058e-08,
          "std": 9.441769573450923e-05,
          "ci95_low": -0.0001172439127185981,
          "ci95_high": 0.00011718860543057094
        },
        "posterior_to_chain_start_jaccard": {
          "n": 5.0,
          "mean": 0.9968572142104829,
          "std": 0.0001975391973890683,
          "ci95_low": 0.9966119762224298,
          "ci95_high": 0.997102452198536
        },
        "dense_magnitude_jaccard": {
          "n": 5.0,
          "mean": 0.1471815613184548,
          "std": 0.004063132067929336,
          "ci95_low": 0.14213732530502937,
          "ci95_high": 0.15222579733188024
        },
        "random_jaccard": {
          "n": 5.0,
          "mean": 0.09177261496255054,
          "std": 8.229787519272847e-05,
          "ci95_low": 0.0916704450357711,
          "ci95_high": 0.09187478488932999
        },
        "posterior_minus_random_jaccard": {
          "n": 5.0,
          "mean": 0.04241776396546274,
          "std": 0.0029458563519041457,
          "ci95_low": 0.03876058658303378,
          "ci95_high": 0.0460749413478917
        },
        "state_num_clusters": {
          "n": 5.0,
          "mean": 3.0,
          "std": 0.0,
          "ci95_low": 3.0,
          "ci95_high": 3.0
        },
        "function_num_clusters": {
          "n": 5.0,
          "mean": 2.2,
          "std": 0.8366600265340756,
          "ci95_low": 1.1613159094315542,
          "ci95_high": 3.238684090568446
        },
        "sample_accuracy": {
          "n": 5.0,
          "mean": 0.885192,
          "std": 0.0026649521571690225,
          "ci95_low": 0.8818835553271448,
          "ci95_high": 0.8885004446728552
        },
        "dense_accuracy": {
          "n": 5.0,
          "mean": 0.8858599999999999,
          "std": 0.0017770762504743748,
          "ci95_low": 0.8836538221373604,
          "ci95_high": 0.8880661778626393
        },
        "imp_accuracy": {
          "n": 5.0,
          "mean": 0.89804,
          "std": 0.0012157302332343291,
          "ci95_low": 0.8965307135375946,
          "ci95_high": 0.8995492864624053
        },
        "sampler_chains": {
          "n": 5.0,
          "mean": 1.0,
          "std": 0.0,
          "ci95_low": 1.0,
          "ci95_high": 1.0
        }
      }
    },
    {
      "label": "CIFAR-10 ResNet-20 long SWAG r5",
      "dataset": "CIFAR-10",
      "model": "ResNet-20",
      "sampler": "SWAG",
      "source_csv": "runs/cifar10_resnet20_long30_rewind1_swag_r5_p0p3_summary.csv",
      "num_runs": 5,
      "metrics": {
        "dense_imp_barrier": {
          "n": 5.0,
          "mean": 3.740163438110352,
          "std": 0.6843357936495588,
          "ci95_low": 2.890584542349186,
          "ci95_high": 4.589742333871518
        },
        "dense_sample_barrier": {
          "n": 5.0,
          "mean": 2.9135016917724608,
          "std": 0.4376149598308698,
          "ci95_low": 2.370218061438101,
          "ci95_high": 3.4567853221068203
        },
        "imp_sample_barrier": {
          "n": 5.0,
          "mean": 2.7180516722412107,
          "std": 0.3115940377412771,
          "ci95_low": 2.3312185985271685,
          "ci95_high": 3.104884745955253
        },
        "posterior_jaccard": {
          "n": 5.0,
          "mean": 0.13608229802578684,
          "std": 0.0024370671442131846,
          "ci95_low": 0.13305676460712026,
          "ci95_high": 0.1391078314444534
        },
        "chain_start_jaccard": {
          "n": 5.0,
          "mean": 0.13613608955119308,
          "std": 0.002499726044994656,
          "ci95_low": 0.13303276730395794,
          "ci95_high": 0.13923941179842822
        },
        "posterior_minus_chain_start_jaccard": {
          "n": 5.0,
          "mean": -5.379152540623267e-05,
          "std": 0.000310187648280578,
          "ci95_low": -0.0004388786159112732,
          "ci95_high": 0.00033129556509880787
        },
        "posterior_to_chain_start_jaccard": {
          "n": 5.0,
          "mean": 0.9265466136684998,
          "std": 0.005285676232821249,
          "ci95_low": 0.919984631935405,
          "ci95_high": 0.9331085954015945
        },
        "dense_magnitude_jaccard": {
          "n": 5.0,
          "mean": 0.1463005092770922,
          "std": 0.0028308239558611534,
          "ci95_low": 0.14278614058144226,
          "ci95_high": 0.14981487797274215
        },
        "random_jaccard": {
          "n": 5.0,
          "mean": 0.09181202951890885,
          "std": 6.513658270986134e-05,
          "ci95_low": 0.09173116473509098,
          "ci95_high": 0.09189289430272672
        },
        "posterior_minus_random_jaccard": {
          "n": 5.0,
          "mean": 0.04427026850687797,
          "std": 0.0024567588381771955,
          "ci95_low": 0.04122028854052405,
          "ci95_high": 0.04732024847323189
        },
        "state_num_clusters": {
          "n": 5.0,
          "mean": 1.0,
          "std": 0.0,
          "ci95_low": 1.0,
          "ci95_high": 1.0
        },
        "function_num_clusters": {
          "n": 5.0,
          "mean": 2.8,
          "std": 0.8366600265340756,
          "ci95_low": 1.7613159094315538,
          "ci95_high": 3.838684090568446
        },
        "sample_accuracy": {
          "n": 5.0,
          "mean": 0.857344,
          "std": 0.009007937055730319,
          "ci95_low": 0.8461609619536042,
          "ci95_high": 0.8685270380463957
        },
        "dense_accuracy": {
          "n": 5.0,
          "mean": 0.8859400000000001,
          "std": 0.0027808272150567203,
          "ci95_low": 0.8824877005052285,
          "ci95_high": 0.8893922994947716
        },
        "imp_accuracy": {
          "n": 5.0,
          "mean": 0.8968999999999999,
          "std": 0.0006164414002969199,
          "ci95_low": 0.8961347096132839,
          "ci95_high": 0.8976652903867159
        },
        "sampler_chains": {
          "n": 5.0,
          "mean": 1.0,
          "std": 0.0,
          "ci95_low": 1.0,
          "ci95_high": 1.0
        }
      }
    },
    {
      "label": "CIFAR-10 ResNet-20 3-chain SGLD r5",
      "dataset": "CIFAR-10",
      "model": "ResNet-20",
      "sampler": "3-chain SGLD",
      "source_csv": "runs/cifar10_resnet20_long30_rewind1_sgld3_r5_p0p3_summary.csv",
      "num_runs": 5,
      "metrics": {
        "dense_imp_barrier": {
          "n": 5.0,
          "mean": 3.2863048370361327,
          "std": 0.2380860005580189,
          "ci95_low": 2.9907294143747603,
          "ci95_high": 3.5818802596975052
        },
        "dense_sample_barrier": {
          "n": 5.0,
          "mean": 3.0077549896850586,
          "std": 0.5501368169623774,
          "ci95_low": 2.3247794186135824,
          "ci95_high": 3.690730560756535
        },
        "imp_sample_barrier": {
          "n": 5.0,
          "mean": 2.8879353829345704,
          "std": 0.17435708609703035,
          "ci95_low": 2.6714771733113785,
          "ci95_high": 3.1043935925577624
        },
        "posterior_jaccard": {
          "n": 5.0,
          "mean": 0.1368358070296329,
          "std": 0.0024964673370908965,
          "ci95_low": 0.13373653035401362,
          "ci95_high": 0.1399350837052522
        },
        "chain_start_jaccard": {
          "n": 5.0,
          "mean": 0.13684068315418013,
          "std": 0.0024579126768253232,
          "ci95_low": 0.13378927073759686,
          "ci95_high": 0.1398920955707634
        },
        "posterior_minus_chain_start_jaccard": {
          "n": 5.0,
          "mean": -4.8761245472428435e-06,
          "std": 4.9915624655349214e-05,
          "ci95_low": -6.684462257035916e-05,
          "ci95_high": 5.709237347587347e-05
        },
        "posterior_to_chain_start_jaccard": {
          "n": 5.0,
          "mean": 0.9969154385516938,
          "std": 0.00018262210926971701,
          "ci95_low": 0.9966887196055643,
          "ci95_high": 0.9971421574978234
        },
        "dense_magnitude_jaccard": {
          "n": 5.0,
          "mean": 0.14598913943280376,
          "std": 0.002054578332382334,
          "ci95_low": 0.1434384524643912,
          "ci95_high": 0.14853982640121632
        },
        "random_jaccard": {
          "n": 5.0,
          "mean": 0.09178909984697141,
          "std": 0.00012657640705609908,
          "ci95_low": 0.09163195967523986,
          "ci95_high": 0.09194624001870295
        },
        "posterior_minus_random_jaccard": {
          "n": 5.0,
          "mean": 0.045046707182661495,
          "std": 0.002595963586143367,
          "ci95_low": 0.04182390940207181,
          "ci95_high": 0.04826950496325118
        },
        "state_num_clusters": {
          "n": 5.0,
          "mean": 3.0,
          "std": 0.0,
          "ci95_low": 3.0,
          "ci95_high": 3.0
        },
        "function_num_clusters": {
          "n": 5.0,
          "mean": 3.2,
          "std": 0.4472135954999579,
          "ci95_low": 2.6448,
          "ci95_high": 3.7552000000000003
        },
        "sample_accuracy": {
          "n": 5.0,
          "mean": 0.8855453333333333,
          "std": 0.000963992277516262,
          "ci95_low": 0.8843485707172981,
          "ci95_high": 0.8867420959493685
        },
        "dense_accuracy": {
          "n": 5.0,
          "mean": 0.88598,
          "std": 0.0023657979626333465,
          "ci95_low": 0.8830429447716462,
          "ci95_high": 0.8889170552283537
        },
        "imp_accuracy": {
          "n": 5.0,
          "mean": 0.899,
          "std": 0.0010440306508910729,
          "ci95_low": 0.8977038725494767,
          "ci95_high": 0.9002961274505233
        },
        "sampler_chains": {
          "n": 5.0,
          "mean": 3.0,
          "std": 0.0,
          "ci95_low": 3.0,
          "ci95_high": 3.0
        }
      }
    },
    {
      "label": "CIFAR-10 ResNet-20 short SWAG r5",
      "dataset": "CIFAR-10",
      "model": "ResNet-20",
      "sampler": "short SWAG",
      "source_csv": "runs/cifar10_resnet20_swag_short_r5_p0p3_summary.csv",
      "num_runs": 5,
      "metrics": {
        "dense_imp_barrier": {
          "n": 5.0,
          "mean": 2.943393923339844,
          "std": 0.3185698625026263,
          "ci95_low": 2.5479006077492747,
          "ci95_high": 3.3388872389304134
        },
        "dense_sample_barrier": {
          "n": 5.0,
          "mean": 2.1717757727050784,
          "std": 0.32194775577745416,
          "ci95_low": 1.772088921039006,
          "ci95_high": 2.5714626243711507
        },
        "imp_sample_barrier": {
          "n": 5.0,
          "mean": 2.0679158143310543,
          "std": 0.21523682857816004,
          "ci95_low": 1.8007068376160213,
          "ci95_high": 2.3351247910460873
        },
        "posterior_jaccard": {
          "n": 5.0,
          "mean": 0.13016306501913116,
          "std": 0.0009227569567157325,
          "ci95_low": 0.12901749460820516,
          "ci95_high": 0.13130863543005716
        },
        "chain_start_jaccard": {
          "n": 5.0,
          "mean": 0.13037214635578145,
          "std": 0.0007555269981850981,
          "ci95_low": 0.1294341860754742,
          "ci95_high": 0.13131010663608872
        },
        "posterior_minus_chain_start_jaccard": {
          "n": 5.0,
          "mean": -0.00020908133665027419,
          "std": 0.00038150015179736537,
          "ci95_low": -0.0006827004001340388,
          "ci95_high": 0.00026453772683349044
        },
        "posterior_to_chain_start_jaccard": {
          "n": 5.0,
          "mean": 0.9096769354058077,
          "std": 0.008052454793973322,
          "ci95_low": 0.8996800950892337,
          "ci95_high": 0.9196737757223817
        },
        "dense_magnitude_jaccard": {
          "n": 5.0,
          "mean": 0.17026909387089706,
          "std": 0.003465745741858424,
          "ci95_low": 0.1659664920375859,
          "ci95_high": 0.17457169570420822
        },
        "random_jaccard": {
          "n": 5.0,
          "mean": 0.09173034912527607,
          "std": 0.00013307757558807213,
          "ci95_low": 0.09156513798073584,
          "ci95_high": 0.0918955602698163
        },
        "posterior_minus_random_jaccard": {
          "n": 5.0,
          "mean": 0.0384327158938551,
          "std": 0.0008350955538961276,
          "ci95_low": 0.037395974041217986,
          "ci95_high": 0.039469457746492215
        },
        "state_num_clusters": {
          "n": 5.0,
          "mean": 1.2,
          "std": 0.4472135954999579,
          "ci95_low": 0.6448,
          "ci95_high": 1.7551999999999999
        },
        "function_num_clusters": {
          "n": 5.0,
          "mean": 2.4,
          "std": 0.8944271909999159,
          "ci95_low": 1.2896,
          "ci95_high": 3.5103999999999997
        },
        "sample_accuracy": {
          "n": 5.0,
          "mean": 0.783136,
          "std": 0.014864159242957515,
          "ci95_low": 0.7646826674208236,
          "ci95_high": 0.8015893325791765
        },
        "dense_accuracy": {
          "n": 5.0,
          "mean": 0.8255399999999999,
          "std": 0.008243664233822228,
          "ci95_low": 0.8153057798674447,
          "ci95_high": 0.8357742201325552
        },
        "imp_accuracy": {
          "n": 5.0,
          "mean": 0.8631399999999999,
          "std": 0.0019112822920751263,
          "ci95_low": 0.8607672100418283,
          "ci95_high": 0.8655127899581715
        },
        "sampler_chains": {
          "n": 5.0,
          "mean": 1.0,
          "std": 0.0,
          "ci95_low": 1.0,
          "ci95_high": 1.0
        }
      }
    }
  ],
  "interpretation_checks": {
    "all_rows_five_seed": true,
    "mnist_dense_imp_barrier_near_zero": true,
    "fashion_dense_imp_barrier_near_zero": true,
    "cifar_dense_imp_barriers_large": true,
    "posterior_never_beats_chain_start": true
  }
}
